{
  "diagnostics": {
    "%2FUsers%2Fdinhmai%2FWorkplace%2FProject%2Fuit": [
      "   "
    ],
    "%2FUsers%2Fdinhmai%2FWorkplace%2FProject%2Fuit%2Fe_wallet%2Fapp%2Fscreens%2Fbuy-train-ticket-screen%2Fcomponents": [
      "error"
    ],
    "%2FUsers%2Fdinhmai%2FWorkplace%2FProject%2Ffun%2FLobo": [
      "fix",
      "tslint"
    ],
    "%2FUsers%2Fdinhmai": [
      "pick"
    ],
    "%2FUsers%2Fdinhmai%2Fworkplace%2Fproject%2Fdotnet%2FHollyPocketWeb": [
      " t"
    ],
    "%2FUsers%2Fdinhmai%2Fworkplace%2Fproject%2Fuit%2Feng-web": [
      " "
    ],
    "%2FUsers%2Fdinhmai%2Fworkplace%2Fproject%2Fhackkerrank": [
      " ="
    ]
  },
  "symbols": {
    "%2FUsers%2Fdinhmai%2FWorkplace%2FProject%2Ffun%2FLobo%2Fapp%2Futils%2Frun-spring": [
      "runSpring",
      "run-spring"
    ],
    "%2FUsers%2Fdinhmai%2FWorkplace%2FProject%2Ffun%2FLobo": [
      "123",
      "console",
      "Home"
    ],
    "%2FUsers%2Fdinhmai%2FWorkplace%2FProject%2Ffun%2Fexpo-app": [
      "react-native-screens"
    ],
    "%2FUsers%2Fnextfuncmac02%2Fworkplace%2Fproject%2Fnextfunc%2Fnugget-mobile-react-native": [
      "StartAFund"
    ],
    "%2FUsers%2Fdinhmai%2FWorkplace%2FProject%2Ffun%2Fcaipu": [
      "useStyleSheet"
    ],
    "%2FUsers%2Fdinhmai%2Fworkplace%2Fproject%2Fdotnet%2FHollyPocketWeb": [
      "logout",
      "signOut"
    ],
    "%2FUsers%2Fdinhmai%2Fworkplace%2Fproject%2Fuit%2Fbowie": [
      "homeScreen",
      "console.log",
      "tlog",
      "balooda",
      "param"
    ]
  },
  "commands": {
    "%2FUsers%2Fdinhmai%2FWorkplace%2FProject%2Ffun%2FLobo": [
      "edit",
      "editsni",
      "org",
      "organ",
      "eslint ",
      "format",
      "editS",
      "autofix",
      "eslin",
      "eslint",
      "es",
      "ts",
      "eslintau",
      "tsorgan",
      "fix"
    ],
    "%2FUsers%2Fdinhmai%2FWorkplace%2FProject%2Ffun%2FWuwu": [
      "or",
      "eslint"
    ],
    "%2FUsers%2Fdinhmai%2FWorkplace%2FProject%2Ffun%2FLobo%2Fapp%2Fscreens%2Fcircle-screen": [
      "snipe"
    ],
    "%2FUsers%2Fdinhmai%2FWorkplace%2FProject%2Ffun%2Fwuwo%2Fapp%2Fscreens%2Fsign-in-screen": [
      "tslint",
      "format"
    ],
    "%2FUsers%2Fdinhmai%2FWorkplace%2FProject%2Ffun%2Fwuwo%2Fapp%2Fscreens%2Fsign-in-screen%2Fcomponents": [
      "dis"
    ],
    "%2FUsers%2Fdinhmai": [
      "make",
      "pick",
      "termi"
    ],
    "%2FUsers%2Fdinhmai%2FWorkplace%2FProject%2Ffun%2Fhackrank%2Fchallenges": [
      "renam"
    ],
    "%2FUsers%2Fdinhmai%2FWorkplace%2FProject%2Ffun%2Fcaipu": [
      "ref"
    ],
    "%2FUsers%2Fdinhmai%2FWorkplace%2FProject%2Fuit%2Fwuwu": [
      "fix",
      "esli"
    ],
    "%2FUsers%2Fdinhmai%2FWorkplace%2FProject%2FTests": [
      "import"
    ],
    "%2FUsers%2Fdinhmai%2Fworkplace%2Fproject%2Fbowie": [
      "edit",
      "snip"
    ],
    "%2FUsers%2Fdinhmai%2Fworkplace%2Fproject%2Fdotnet%2FHollypocketBackend": [
      "import"
    ],
    "%2FUsers%2Fdinhmai%2Fworkplace%2Fproject%2Fdotnet%2FHollyPocketWeb": [
      "fix",
      "editsn",
      "eslit"
    ],
    "%2FUsers%2Fdinhmai%2Fworkplace%2Fproject%2Fuit%2Feng-web": [
      "eslint"
    ],
    "%2FUsers%2Fdinhmai%2Fworkplace%2Fproject%2Ffun%2Fnode-playground%2Fbowie-backend": [
      "esli"
    ],
    "%2FUsers%2Fdinhmai%2Fworkplace%2Fproject%2Fuit%2Fbowie": [
      "deno",
      "toggle",
      "esli",
      "ts",
      "eslint",
      "yank",
      "tss"
    ],
    "%2FUsers%2Fdinhmai%2Fworkplace%2Fproject%2Ffun%2Fdeno-playground": [
      "d"
    ],
    "%2FUsers%2Fdinhmai%2Fworkplace%2Fproject%2Fdotnet%2FHollypocket": [
      "eslint"
    ],
    "%2FUsers%2Fdinhmai%2Fworkplace%2Fproject%2Fdotnet%2Fholly-admin": [
      "tsserver",
      "tsser",
      "ts",
      "eslint"
    ],
    "%2FUsers%2Fdinhmai%2Fworkspace%2Fproject%2Fuit%2FHollypocket%2Fweb": [
      "yank"
    ],
    "%2FUsers%2Fdinhmai%2Fworkspace%2Fproject%2Fuit%2FHollypocket": [
      "cl"
    ],
    "%2FUsers%2Fdinhmai%2Fworkspace%2Fproject%2Fuit%2FBowie": [
      "res",
      "tsser",
      "yan"
    ],
    "%2FUsers%2Fdinhmai%2Fworkspace%2Fproject%2Fuit%2FBowie%2Fmobile": [
      "yank"
    ],
    "%2FUsers%2Fdinhmai%2F": {
      "config": [
        "yank"
      ]
    },
    "%2FUsers%2Fdinhmai%2Fworkspace%2Fproject%2Ffun%2FBowie": [
      "ya",
      "tsse",
      "y",
      "yan",
      "ts"
    ],
    "%2FUsers%2Fdinhmai%2Fworkspace%2Fproject%2Ffun%2Ftesting": [
      "clea"
    ]
  },
  "extensions": {
    "%2FUsers%2Fdinhmai%2FWorkplace%2FProject%2Ffun%2FLobo": [
      "par"
    ],
    "%2FUsers%2Fdinhmai%2FWorkplace%2FProject%2Ffun%2Fwuwo": [
      "spe"
    ],
    "%2FUsers%2Fdinhmai%2FWorkplace%2FProject%2Ffun%2Fcaipu": [
      " e"
    ],
    "%2FUsers%2Fdinhmai%2FWorkplace%2FProject%2Fuit%2Feng-web": [
      "prett"
    ],
    "%2FUsers%2Fdinhmai%2F": {
      "config": [
        " e",
        "ya"
      ]
    },
    "%2FUsers%2Fdinhmai%2Fworkplace%2Fproject%2Fuit%2Fbowie": [
      "nin",
      "deno ",
      "deno"
    ],
    "%2FUsers%2Fdinhmai%2FDocuments%2Feng": [
      " e"
    ],
    "%2FUsers%2Fdinhmai%2Fworkplace%2Fproject%2Fuit%2Feng-web": [
      "word e"
    ],
    "%2FUsers%2Fdinhmai%2Fworkplace%2Fproject%2Fuit%2Fbowie-backend": [
      "deno "
    ],
    "%2FUsers%2Fdinhmai%2Fworkplace%2Fproject%2Ffun%2Fdeno-playground": [
      "deno e",
      "deno"
    ],
    "%2FUsers%2Fdinhmai%2Fworkplace%2Fproject%2Fdotnet%2FHollypocket": [
      "csh"
    ],
    "%2FUsers%2Fdinhmai%2Fworkplace%2Fproject%2Fhackkerrank": [
      "deno"
    ],
    "%2FUsers%2Fdinhmai%2Fworkplace%2Fproject%2Ffun%2FReanimatedPlayground": [
      "deno"
    ],
    "%2FUsers%2Fdinhmai%2Fworkplace%2Fproject%2Fdotnet%2Fholly-admin": [
      "tail"
    ]
  },
  "marketplace": {
    "%2FUsers%2Fdinhmai%2FWorkplace%2FProject%2Ffun%2Fwuwo%2Fapp%2Fscreens%2Fsign-in-screen": [
      "tree"
    ],
    "%2FUsers%2Fdinhmai": [
      "termi"
    ],
    "%2FUsers%2Fnextfuncmac02%2Fworkplace%2Fproject%2Fnextfunc%2Fnugget-mobile-react-native": [
      "high"
    ],
    "%2FUsers%2Fdinhmai%2FWorkplace%2FProject%2Ffun%2Fcaipu": [
      "denite"
    ],
    "%2FUsers%2Fdinhmai%2FWorkplace%2FProject%2Fuit%2Fwuwu": [
      "loremis"
    ],
    "%2FUsers%2Fdinhmai%2FWorkplace%2FProject%2Fpython-project%2Ftutorial%2Ftutorial%2Fspiders": [
      "python"
    ],
    "%2FUsers%2Fdinhmai%2F": {
      "config": [
        "coc-yank",
        "omni",
        "css"
      ]
    },
    "%2FUsers%2Fdinhmai%2Fworkplace%2Fproject%2Fuit%2Fbowie": [
      "syntax",
      "styled"
    ],
    "%2FUsers%2Fdinhmai%2Fworkplace%2Fproject%2Fdotnet%2FHollyPocketWeb": [
      "tail",
      "styled",
      "scss",
      "css",
      "taiw",
      "taiwind",
      "em",
      "emm",
      "cs"
    ],
    "%2FUsers%2Fdinhmai%2Fworkplace%2Fproject%2Fuit%2Feng-web": [
      "json"
    ],
    "%2FUsers%2Fdinhmai%2Fworkplace%2Fproject%2Fuit%2Fbowie-backend": [
      "deno"
    ]
  },
  "outline": {
    "%2FUsers%2Fdinhmai%2F": {
      "config": [
        "fd"
      ]
    },
    "%2FUsers%2Fdinhmai%2FWorkplace%2FProject%2Ffun%2Fhackrank%2Fchallenges": [
      "non"
    ]
  },
  "explorerActions": {
    "%2FUsers%2Fdinhmai%2Fworkplace%2Fproject%2Fuit%2Fbowie": [
      "open"
    ],
    "%2FUsers%2Fdinhmai%2Fworkspace%2Fproject%2Fuit%2FHollypocket": [
      "renam"
    ],
    "%2FUsers%2Fdinhmai%2Fworkspace%2Fproject%2Ffun%2FBowie": [
      "past",
      "copy",
      "pas"
    ]
  }
}