{
  "suggest.noselect": false,
  "coc.preferences.formatOnSaveFiletypes": [
    "javascript",
    "typescript",
    "typescriptreact",
    "json",
    "javascriptreact",
    "typescript.tsx",
    "graphql",
    "python",
    "cs",
    "csharp",
    "scss"
  ],
  "diagnostic.errorSign": "✖",
  "diagnostic.warningSign": "⚠",
  "diagnostic.infoSign": "",
  "tailwindCSS.emmetCompletions": true,
  "typescript.showUnused": false,
  "yank.enableCompletion": false,
  "coc.preferences.formatOnType": false,
  "tsserver.log": "verbose",
  "tsserver.npm": "/usr/local/bin/npm",
  "coc.preferences.colorSupport": true,
  "explorer.width": 30,
  "explorer.icon.enableNerdfont": true,
  "explorer.previewAction.onHover": false,
  "explorer.keyMappings": {
    "<cr>": ["expandable?", "expand", "open"],
    "v": "open:vsplit"
  },
  "floatinput.status.enabled": true
}
